evolvingfuzzysystems/__init__
evolvingfuzzysystems/classification.py
evolvingfuzzysystems/eFS.py
evolvingfuzzysystems-0.1.5.dist-info/METADATA
evolvingfuzzysystems-0.1.5.dist-info/WHEEL
evolvingfuzzysystems-0.1.5.dist-info/licenses/LICENSE
evolvingfuzzysystems-0.1.5.dist-info/RECORD
