Metadata-Version: 2.4
Name: evolvingfuzzysystems
Version: 0.1.5
Summary: eFS (evolving Fuzzy Systems)
Project-URL: Homepage, https://github.com/kaikerochaalves/evolvingfuzzysystems.git
Project-URL: Issues, https://github.com/kaikerochaalves/evolvingfuzzysystems.git
Author-email: Kaike Sa Teles Rocha Alves <kaikerochaalves@outlook.com>
License-File: LICENSE
Classifier: License :: OSI Approved :: GNU General Public License v3 (GPLv3)
Classifier: Programming Language :: Python :: 3
Requires-Python: >=3.0
Requires-Dist: matplotlib
Requires-Dist: numpy
Requires-Dist: pandas
Requires-Dist: scipy
